ardkit/__init__.py
ardkit/__main__.py
ardkit/api/__init__.py
ardkit/core/__init__.py
ardkit/core/db/__init__.py
ardkit/core/event/__init__.py
ardkit/core/iokit.py
ardkit/core/log/__init__.py
ardkit/core/net/__init__.py
ardkit/core/system/__init__.py
ardkit-4.1.0.dist-info/LICENSE
ardkit-4.1.0.dist-info/WHEEL
ardkit-4.1.0.dist-info/METADATA
ardkit-4.1.0.dist-info/RECORD
